setup.cfg
setup.py
relalg/__init__.py
relalg/relalg.py
relalg.egg-info/PKG-INFO
relalg.egg-info/SOURCES.txt
relalg.egg-info/dependency_links.txt
relalg.egg-info/entry_points.txt
relalg.egg-info/top_level.txt
relalg.egg-info/zip-safe