Metadata-Version: 1.1
Name: relalg
Version: 0.2.1
Summary: Relational algebra for python
Home-page: http://reshefmann.com
Author: Reshef Mann
Author-email: reshef.mann@gmail.com
License: MIT
Keywords: Data,Relational Algebra,Join
Platform: UNKNOWN
Classifier: Development Status :: 3 - Alpha
Classifier: License :: OSI Approved :: MIT License
